MetasploitZhongwenWiki/README.md
MetasploitZhongwenWiki/__init__.py
MetasploitZhongwenWiki/__main__.py
MetasploitZhongwenWiki/file.epub
MetasploitZhongwenWiki/index.html
MetasploitZhongwenWiki/css/__init__.py
MetasploitZhongwenWiki/css/annotations.css
MetasploitZhongwenWiki/css/main.css
MetasploitZhongwenWiki/css/normalize.css
MetasploitZhongwenWiki/css/popup.css
MetasploitZhongwenWiki/font/__init__.py
MetasploitZhongwenWiki/font/fontello.eot
MetasploitZhongwenWiki/font/fontello.svg
MetasploitZhongwenWiki/font/fontello.ttf
MetasploitZhongwenWiki/font/fontello.woff
MetasploitZhongwenWiki/img/__init__.py
MetasploitZhongwenWiki/img/annotator-glyph-sprite.png
MetasploitZhongwenWiki/img/annotator-icon-sprite.png
MetasploitZhongwenWiki/img/apple-touch-icon.png
MetasploitZhongwenWiki/img/cancelfullscreen.png
MetasploitZhongwenWiki/img/close.png
MetasploitZhongwenWiki/img/fullscreen.png
MetasploitZhongwenWiki/img/loader.gif
MetasploitZhongwenWiki/img/menu-icon.png
MetasploitZhongwenWiki/img/save.png
MetasploitZhongwenWiki/img/saved.png
MetasploitZhongwenWiki/img/settings-s.png
MetasploitZhongwenWiki/img/settings.png
MetasploitZhongwenWiki/img/star.png
MetasploitZhongwenWiki/js/__init__.py
MetasploitZhongwenWiki/js/epub.js
MetasploitZhongwenWiki/js/epub.min.js
MetasploitZhongwenWiki/js/epub.min.map
MetasploitZhongwenWiki/js/hooks.min.js
MetasploitZhongwenWiki/js/hooks.min.map
MetasploitZhongwenWiki/js/reader.js
MetasploitZhongwenWiki/js/reader.js.map
MetasploitZhongwenWiki/js/reader.min.js
MetasploitZhongwenWiki/js/reader.min.map
MetasploitZhongwenWiki/js/hooks/__init__.py
MetasploitZhongwenWiki/js/hooks/extensions/__init__.py
MetasploitZhongwenWiki/js/hooks/extensions/highlight.js
MetasploitZhongwenWiki/js/libs/__init__.py
MetasploitZhongwenWiki/js/libs/jquery.min.js
MetasploitZhongwenWiki/js/libs/localforage.min.js
MetasploitZhongwenWiki/js/libs/screenfull.js
MetasploitZhongwenWiki/js/libs/screenfull.min.js
MetasploitZhongwenWiki/js/libs/zip.min.js
metasploit_zhongwen_wiki-2024.3.3.0.dist-info/METADATA
metasploit_zhongwen_wiki-2024.3.3.0.dist-info/WHEEL
metasploit_zhongwen_wiki-2024.3.3.0.dist-info/entry_points.txt
metasploit_zhongwen_wiki-2024.3.3.0.dist-info/top_level.txt
metasploit_zhongwen_wiki-2024.3.3.0.dist-info/RECORD
